terminal_coding_agent/__init__.py
terminal_coding_agent/agent.py
terminal_coding_agent-0.1.1.dist-info/licenses/LICENSE
terminal_coding_agent-0.1.1.dist-info/METADATA
terminal_coding_agent-0.1.1.dist-info/WHEEL
terminal_coding_agent-0.1.1.dist-info/entry_points.txt
terminal_coding_agent-0.1.1.dist-info/top_level.txt
terminal_coding_agent-0.1.1.dist-info/RECORD
