Metadata-Version: 2.4
Name: terminal-coding-agent
Version: 0.1.1
Summary: Terminal-based AI coding assistant using OpenAI
Home-page: https://github.com/KeshavTiwari373/terminal-coding-agent
Author: Keshav Tiwari
Author-email: keshav.tiwari623@email.com
Classifier: Programming Language :: Python :: 3
Classifier: License :: OSI Approved :: MIT License
Classifier: Operating System :: OS Independent
Requires-Python: >=3.7
License-File: LICENSE
Requires-Dist: openai>=1.0.0
Requires-Dist: rich
Requires-Dist: python-dotenv
Dynamic: author
Dynamic: author-email
Dynamic: classifier
Dynamic: description
Dynamic: description-content-type
Dynamic: home-page
Dynamic: license-file
Dynamic: requires-dist
Dynamic: requires-python
Dynamic: summary
